{
  "schema_version": 3,
  "metadata": {
    "job_id": "20260529T113454_cc77cb",
    "label": "sweep:polar3bet_field:s3",
    "mode": "ab",
    "created_at": "2026-05-29T11:34:54Z",
    "started_at": "2026-05-29T11:47:41Z",
    "completed_at": "2026-05-29T11:48:44Z"
  },
  "mode": "ab",
  "opponents": [
    {
      "id": "polar_3bettor",
      "path": "/home/lucas/projects/fullhouse-hackathon-write-up-repo/bots/custom/polar_3bettor/bot.py"
    },
    {
      "id": "squeezer",
      "path": "/home/lucas/projects/fullhouse-hackathon-write-up-repo/bots/custom/squeezer/bot.py"
    },
    {
      "id": "polar_3bettor",
      "path": "/home/lucas/projects/fullhouse-hackathon-write-up-repo/bots/custom/polar_3bettor/bot.py"
    },
    {
      "id": "squeezer",
      "path": "/home/lucas/projects/fullhouse-hackathon-write-up-repo/bots/custom/squeezer/bot.py"
    },
    {
      "id": "competent_tag",
      "path": "/home/lucas/projects/fullhouse-hackathon-write-up-repo/bots/custom/competent_tag/bot.py"
    }
  ],
  "preset_name": "polar3bet_field",
  "params": {
    "matches": 100,
    "hands": 1000,
    "seed_base": 3,
    "budget": 2.0,
    "fold_on_timeout": true,
    "workers": 21,
    "big_blind": 100,
    "starting_stack": 10000
  },
  "elapsed_s": 63.33,
  "stats": {
    "v12_cont": {
      "matches": 100,
      "total_delta": 2632912,
      "mean_delta": 26329.12,
      "stdev": 25790.687550134968,
      "stderr": 2579.0687550134967,
      "ci95": 5054.974759826453,
      "ci_low": 21274.145240173544,
      "ci_high": 31384.094759826454,
      "bb_per_100": 26.32912,
      "win_rate": 0.7
    },
    "v12_cbet_cont": {
      "matches": 100,
      "total_delta": 2582301,
      "mean_delta": 25823.01,
      "stdev": 26249.16876432625,
      "stderr": 2624.916876432625,
      "ci95": 5144.837077807945,
      "ci_low": 20678.172922192054,
      "ci_high": 30967.847077807943,
      "bb_per_100": 25.823009999999996,
      "win_rate": 0.67
    },
    "v12_cbet": {
      "matches": 100,
      "total_delta": 2371800,
      "mean_delta": 23718.0,
      "stdev": 26876.97083062567,
      "stderr": 2687.697083062567,
      "ci95": 5267.886282802631,
      "ci_low": 18450.113717197368,
      "ci_high": 28985.886282802632,
      "bb_per_100": 23.718,
      "win_rate": 0.64
    },
    "v7_m2": {
      "matches": 100,
      "total_delta": 2557673,
      "mean_delta": 25576.73,
      "stdev": 26174.925749985858,
      "stderr": 2617.492574998586,
      "ci95": 5130.285446997228,
      "ci_low": 20446.444553002773,
      "ci_high": 30707.015446997226,
      "bb_per_100": 25.576729999999998,
      "win_rate": 0.68
    }
  },
  "per_match_deltas": {
    "v12_cont": [
      50000,
      182,
      50000,
      -10000,
      36981,
      50000,
      -10000,
      44556,
      -10000,
      -10000,
      -10000,
      6285,
      50000,
      -10000,
      34983,
      49040,
      50000,
      -10000,
      50000,
      22112,
      24836,
      50000,
      35099,
      50000,
      50000,
      -10000,
      50000,
      50000,
      -10000,
      -10000,
      -10000,
      50000,
      16261,
      48947,
      -10000,
      -10000,
      46376,
      50000,
      27077,
      -10000,
      38094,
      50000,
      -10000,
      17445,
      50000,
      50000,
      -10000,
      27670,
      50000,
      -10000,
      46841,
      50000,
      39796,
      50000,
      -10000,
      -10000,
      50000,
      23976,
      27326,
      45722,
      46859,
      -10000,
      46903,
      50000,
      37069,
      50000,
      50000,
      30262,
      50000,
      -10000,
      23161,
      45964,
      -10000,
      48080,
      50000,
      50000,
      22678,
      37148,
      29909,
      -10000,
      29471,
      50000,
      50000,
      50000,
      -10000,
      50000,
      -2590,
      31969,
      50000,
      -10000,
      50000,
      -10000,
      50000,
      -10000,
      50000,
      50000,
      50000,
      -10000,
      -10000,
      36424
    ],
    "v12_cbet_cont": [
      50000,
      -918,
      50000,
      -10000,
      36386,
      50000,
      -10000,
      44420,
      -10000,
      -10000,
      -10000,
      20219,
      50000,
      -10000,
      48327,
      50000,
      50000,
      -10000,
      50000,
      26256,
      25306,
      50000,
      41627,
      50000,
      50000,
      -10000,
      50000,
      50000,
      -10000,
      -10000,
      -10000,
      50000,
      -10000,
      48272,
      -10000,
      -10000,
      44438,
      50000,
      27077,
      -10000,
      35587,
      50000,
      -10000,
      17445,
      50000,
      50000,
      -10000,
      27670,
      50000,
      -10000,
      46841,
      49846,
      37546,
      50000,
      -10000,
      -10000,
      50000,
      16436,
      28026,
      43922,
      46859,
      -10000,
      46903,
      50000,
      37029,
      50000,
      50000,
      27662,
      50000,
      -10000,
      25066,
      45964,
      -10000,
      48080,
      50000,
      50000,
      23378,
      -10000,
      29227,
      -10000,
      29471,
      50000,
      50000,
      50000,
      -10000,
      50000,
      -1155,
      33721,
      50000,
      -10000,
      50000,
      -10000,
      50000,
      -10000,
      50000,
      50000,
      50000,
      -10000,
      -10000,
      35367
    ],
    "v12_cbet": [
      50000,
      -10000,
      50000,
      -10000,
      50000,
      50000,
      -10000,
      28086,
      -10000,
      -10000,
      -10000,
      13963,
      37964,
      -10000,
      -10000,
      49705,
      50000,
      -10000,
      50000,
      27112,
      17059,
      49318,
      49354,
      50000,
      50000,
      -10000,
      50000,
      50000,
      -10000,
      -10000,
      -10000,
      50000,
      -10000,
      48426,
      -10000,
      -10000,
      46842,
      40098,
      -10000,
      -10000,
      50000,
      50000,
      -10000,
      18665,
      50000,
      50000,
      -10000,
      33636,
      50000,
      -10000,
      41905,
      42458,
      33125,
      50000,
      -10000,
      -10000,
      50000,
      50000,
      23806,
      44913,
      23693,
      -10000,
      38828,
      50000,
      37991,
      50000,
      50000,
      24056,
      50000,
      -10000,
      -10000,
      37379,
      -10000,
      50000,
      50000,
      46978,
      15904,
      -10000,
      46210,
      -10000,
      30340,
      50000,
      50000,
      50000,
      -10000,
      18378,
      -10000,
      29744,
      50000,
      -10000,
      50000,
      -10000,
      50000,
      -10000,
      50000,
      50000,
      50000,
      -10000,
      -10000,
      35864
    ],
    "v7_m2": [
      50000,
      -10000,
      50000,
      -10000,
      50000,
      50000,
      -10000,
      28086,
      50000,
      -10000,
      -10000,
      12763,
      37964,
      -10000,
      38291,
      46057,
      50000,
      -10000,
      50000,
      27387,
      13633,
      48606,
      49307,
      50000,
      50000,
      -10000,
      50000,
      50000,
      -10000,
      -10000,
      -10000,
      50000,
      16473,
      48476,
      -10000,
      -10000,
      46468,
      40098,
      -10000,
      -10000,
      50000,
      50000,
      -10000,
      18665,
      50000,
      50000,
      -10000,
      33636,
      50000,
      28130,
      41905,
      42133,
      33125,
      50000,
      -10000,
      -10000,
      50000,
      50000,
      24406,
      44913,
      23693,
      -10000,
      38828,
      41434,
      38041,
      50000,
      50000,
      23661,
      50000,
      -10000,
      -10000,
      37379,
      -10000,
      50000,
      50000,
      46586,
      13004,
      -10000,
      46930,
      -10000,
      30340,
      50000,
      50000,
      50000,
      -10000,
      50000,
      -10000,
      30481,
      50000,
      -10000,
      50000,
      -10000,
      50000,
      -10000,
      50000,
      50000,
      50000,
      -10000,
      -10000,
      36774
    ]
  },
  "per_match_ev_deltas": {
    "v12_cont": [
      47970.511,
      182.0,
      46032.4957,
      -10000.0,
      36981.0,
      46617.1039,
      -10000.0,
      41750.4255,
      -10000.0,
      -6415.5125,
      -10000.0,
      6285.0,
      48027.7105,
      -10000.0,
      34983.0,
      50458.0175,
      49960.4775,
      -20218.8827,
      49006.8525,
      22112.0,
      24144.7273,
      47944.1285,
      33733.4224,
      49576.2195,
      49809.7993,
      -10000.0,
      48138.7647,
      48593.3295,
      -10000.0,
      -10000.0,
      -10000.0,
      47857.1875,
      18049.023,
      48947.0,
      -17859.9631,
      -10000.0,
      48024.351,
      50000.0,
      27077.0,
      -10000.0,
      38094.0,
      47944.1028,
      -8356.995,
      18033.808,
      48468.0973,
      47841.0005,
      7636.1111,
      27670.0,
      49400.778,
      -10000.0,
      44746.6525,
      49962.3565,
      39760.925,
      48041.4475,
      -10000.0,
      -10000.0,
      50000.0,
      23954.976,
      19387.3239,
      45757.9464,
      46859.0,
      -10000.0,
      46931.4625,
      49514.35,
      37591.8182,
      48278.8475,
      -6671.1531,
      30225.3045,
      46283.0215,
      -4780.5238,
      23161.0,
      19926.1997,
      -10000.0,
      49118.6225,
      50000.0,
      50000.0,
      22678.0,
      37148.0,
      30536.859,
      -9568.3182,
      29471.0,
      48358.928,
      41921.6995,
      44325.1782,
      -9938.2188,
      50000.0,
      3642.1,
      31969.0,
      48475.7273,
      -6095.848,
      48942.606,
      -10000.0,
      50000.0,
      4448.4112,
      50000.0,
      39440.1435,
      49957.0625,
      -10000.0,
      -8583.3333,
      36424.0
    ],
    "v12_cbet_cont": [
      47970.511,
      -918.0,
      46032.4957,
      -10000.0,
      36386.0,
      46537.8522,
      -10000.0,
      41661.0945,
      -10000.0,
      -6415.5125,
      -10000.0,
      18291.5615,
      48027.7105,
      -10000.0,
      46867.344,
      50610.0875,
      50028.57,
      -19413.2523,
      48894.5535,
      26256.0,
      24625.1818,
      49714.7808,
      38510.3169,
      49635.132,
      48829.7355,
      -10000.0,
      48138.7647,
      47755.6778,
      -10000.0,
      -10000.0,
      -10000.0,
      47857.1875,
      -8327.7778,
      49467.425,
      -17859.9631,
      -10000.0,
      44438.0,
      48271.7118,
      27077.0,
      -10000.0,
      34524.5885,
      49228.075,
      -8356.995,
      18033.808,
      48468.0973,
      47608.838,
      7636.1111,
      27670.0,
      49414.4143,
      -10000.0,
      44746.6525,
      49837.8512,
      37510.925,
      47788.465,
      -10000.0,
      -10000.0,
      50000.0,
      16436.0,
      20071.4148,
      44742.3276,
      46859.0,
      -10000.0,
      46931.4625,
      49580.8375,
      37553.6364,
      48278.8475,
      -6671.1531,
      27908.8175,
      46283.0215,
      -6631.9524,
      25066.0,
      20041.6872,
      -10000.0,
      49118.6225,
      50000.0,
      46572.1963,
      23378.0,
      -9143.9682,
      30473.3101,
      -9599.1364,
      29471.0,
      48358.928,
      41783.6685,
      44301.9459,
      -9938.2188,
      50000.0,
      5077.1,
      33721.0,
      48566.6364,
      -7104.016,
      49322.588,
      -10000.0,
      44289.5455,
      4448.4112,
      50000.0,
      39523.874,
      47675.8175,
      -10000.0,
      -8583.3333,
      35367.0
    ],
    "v12_cbet": [
      48625.0,
      4098.3182,
      49969.9832,
      -10000.0,
      50006.825,
      49946.4425,
      -10000.0,
      24146.3665,
      -10000.0,
      -6415.5125,
      -10000.0,
      15775.0605,
      37964.0,
      -10000.0,
      -235.6405,
      49682.5225,
      50000.0,
      -12719.6263,
      48894.5535,
      27112.0,
      17059.0,
      49307.5523,
      44896.5295,
      49653.1995,
      52016.3497,
      -10000.0,
      49295.0922,
      50862.6905,
      -10000.0,
      -10000.0,
      -10000.0,
      47612.2025,
      -8327.7778,
      49616.457,
      -17845.8722,
      -10000.0,
      47774.668,
      42756.6905,
      -10000.0,
      -10000.0,
      48141.8938,
      48090.6888,
      -10000.0,
      19253.808,
      48897.4105,
      47413.9515,
      7636.1111,
      33636.0,
      49295.3057,
      -10000.0,
      40427.197,
      42458.0,
      33125.0,
      48053.545,
      -10000.0,
      -9736.2727,
      49995.674,
      53819.0496,
      25505.698,
      45689.2828,
      25905.565,
      -10000.0,
      38828.0,
      50000.0,
      38666.1818,
      62437.0033,
      11177.0952,
      22847.17,
      46332.6615,
      -7994.2857,
      -10000.0,
      12911.876,
      -10000.0,
      49997.417,
      47581.4667,
      46978.0,
      15904.0,
      -8940.4453,
      44878.4606,
      -9474.5952,
      30340.0,
      50854.743,
      43008.1603,
      45651.6166,
      -9938.2188,
      18504.7683,
      -1749.625,
      29744.0,
      48388.1818,
      -6115.126,
      48588.4685,
      -10000.0,
      50000.0,
      4684.2378,
      50000.0,
      39490.7893,
      49990.6378,
      -10000.0,
      -10000.0,
      36364.192
    ],
    "v7_m2": [
      48625.0,
      4135.8182,
      50421.4597,
      -10000.0,
      49972.6837,
      50095.7863,
      -10000.0,
      24124.9935,
      49240.0175,
      -6415.5125,
      -10000.0,
      14575.0605,
      37964.0,
      -10000.0,
      38291.0,
      46057.0,
      50000.0,
      -12865.6465,
      49006.8525,
      27387.0,
      13633.0,
      49114.0605,
      42584.6745,
      49749.4995,
      50091.6957,
      -10000.0,
      49295.0922,
      50061.114,
      -10000.0,
      -10000.0,
      -10000.0,
      47612.2025,
      19475.7159,
      49697.507,
      -17845.8722,
      -10000.0,
      49193.1755,
      42756.6905,
      -10000.0,
      -10000.0,
      48325.3855,
      47261.9142,
      -10000.0,
      19253.808,
      48897.4105,
      47508.5205,
      7636.1111,
      33636.0,
      49199.3718,
      28130.0,
      40427.197,
      42133.0,
      33125.0,
      48041.4475,
      -10000.0,
      -9736.2727,
      49995.674,
      55395.0101,
      25989.373,
      45689.2828,
      25905.565,
      -10000.0,
      38828.0,
      41434.0,
      38713.9091,
      62437.0033,
      11177.0952,
      22315.72,
      46332.6615,
      -7751.2857,
      -10000.0,
      13238.765,
      -10000.0,
      49997.417,
      47631.9515,
      47987.903,
      13004.0,
      -8943.1502,
      45657.1636,
      -10000.0,
      30340.0,
      50854.743,
      41867.5325,
      43779.7762,
      -9938.2188,
      50000.0,
      -1717.04,
      30481.0,
      48342.7273,
      -6828.055,
      48582.0305,
      -10000.0,
      50000.0,
      4684.2378,
      50000.0,
      39490.7893,
      47574.4475,
      -10000.0,
      -10000.0,
      37197.192
    ]
  },
  "per_match_placement": {
    "v12_cont": [
      1.0,
      2.0,
      1.0,
      4.0,
      1.0,
      1.0,
      4.5,
      1.0,
      4.5,
      4.0,
      4.0,
      2.0,
      1.0,
      4.5,
      1.0,
      1.0,
      1.0,
      4.0,
      1.0,
      1.0,
      1.0,
      1.0,
      1.0,
      1.0,
      1.0,
      4.5,
      1.0,
      1.0,
      4.5,
      4.0,
      4.5,
      1.0,
      2.0,
      1.0,
      4.0,
      4.0,
      1.0,
      1.0,
      1.0,
      4.0,
      1.0,
      1.0,
      4.5,
      2.0,
      1.0,
      1.0,
      4.5,
      1.0,
      1.0,
      4.0,
      1.0,
      1.0,
      1.0,
      1.0,
      4.5,
      4.5,
      1.0,
      1.0,
      1.0,
      1.0,
      1.0,
      4.5,
      1.0,
      1.0,
      1.0,
      1.0,
      1.0,
      1.0,
      1.0,
      5.0,
      1.0,
      1.0,
      4.5,
      1.0,
      1.0,
      1.0,
      1.0,
      1.0,
      1.0,
      4.0,
      1.0,
      1.0,
      1.0,
      1.0,
      5.0,
      1.0,
      3.0,
      1.0,
      1.0,
      4.5,
      1.0,
      4.5,
      1.0,
      4.0,
      1.0,
      1.0,
      1.0,
      4.0,
      5.0,
      1.0
    ],
    "v12_cbet_cont": [
      1.0,
      2.0,
      1.0,
      4.0,
      1.0,
      1.0,
      4.5,
      1.0,
      4.5,
      4.0,
      4.0,
      1.0,
      1.0,
      4.5,
      1.0,
      1.0,
      1.0,
      4.0,
      1.0,
      1.0,
      1.0,
      1.0,
      1.0,
      1.0,
      1.0,
      4.5,
      1.0,
      1.0,
      4.5,
      4.0,
      4.5,
      1.0,
      5.0,
      1.0,
      4.0,
      4.0,
      1.0,
      1.0,
      1.0,
      4.0,
      1.0,
      1.0,
      4.5,
      2.0,
      1.0,
      1.0,
      4.5,
      1.0,
      1.0,
      5.0,
      1.0,
      1.0,
      1.0,
      1.0,
      4.5,
      4.5,
      1.0,
      2.0,
      1.0,
      1.0,
      1.0,
      4.5,
      1.0,
      1.0,
      1.0,
      1.0,
      1.0,
      1.0,
      1.0,
      5.0,
      1.0,
      1.0,
      4.5,
      1.0,
      1.0,
      1.0,
      1.0,
      4.5,
      1.0,
      4.0,
      1.0,
      1.0,
      1.0,
      1.0,
      5.0,
      1.0,
      3.0,
      1.0,
      1.0,
      4.5,
      1.0,
      4.5,
      1.0,
      4.0,
      1.0,
      1.0,
      1.0,
      4.0,
      5.0,
      1.0
    ],
    "v12_cbet": [
      1.0,
      4.5,
      1.0,
      4.0,
      1.0,
      1.0,
      4.5,
      1.0,
      4.5,
      4.0,
      4.5,
      2.0,
      1.0,
      4.5,
      4.5,
      1.0,
      1.0,
      5.0,
      1.0,
      1.0,
      1.0,
      1.0,
      1.0,
      1.0,
      1.0,
      4.5,
      1.0,
      1.0,
      4.5,
      4.0,
      4.5,
      1.0,
      5.0,
      1.0,
      4.0,
      4.0,
      1.0,
      1.0,
      4.0,
      4.0,
      1.0,
      1.0,
      4.5,
      2.0,
      1.0,
      1.0,
      4.5,
      1.0,
      1.0,
      4.0,
      1.0,
      1.0,
      1.0,
      1.0,
      4.5,
      4.5,
      1.0,
      1.0,
      1.0,
      1.0,
      1.0,
      4.5,
      1.0,
      1.0,
      1.0,
      1.0,
      1.0,
      1.0,
      1.0,
      4.5,
      5.0,
      1.0,
      4.5,
      1.0,
      1.0,
      1.0,
      2.0,
      4.5,
      1.0,
      4.5,
      1.0,
      1.0,
      1.0,
      1.0,
      5.0,
      2.0,
      4.5,
      1.0,
      1.0,
      4.5,
      1.0,
      4.5,
      1.0,
      4.0,
      1.0,
      1.0,
      1.0,
      4.0,
      5.0,
      1.0
    ],
    "v7_m2": [
      1.0,
      4.5,
      1.0,
      4.0,
      1.0,
      1.0,
      4.5,
      1.0,
      1.0,
      4.0,
      4.5,
      2.0,
      1.0,
      4.5,
      1.0,
      1.0,
      1.0,
      5.0,
      1.0,
      1.0,
      1.0,
      1.0,
      1.0,
      1.0,
      1.0,
      4.5,
      1.0,
      1.0,
      4.5,
      4.0,
      4.5,
      1.0,
      1.0,
      1.0,
      4.0,
      4.0,
      1.0,
      1.0,
      4.0,
      4.0,
      1.0,
      1.0,
      4.5,
      2.0,
      1.0,
      1.0,
      4.5,
      1.0,
      1.0,
      1.0,
      1.0,
      1.0,
      1.0,
      1.0,
      4.5,
      4.5,
      1.0,
      1.0,
      1.0,
      1.0,
      1.0,
      4.5,
      1.0,
      1.0,
      1.0,
      1.0,
      1.0,
      1.0,
      1.0,
      4.5,
      5.0,
      1.0,
      4.5,
      1.0,
      1.0,
      1.0,
      2.0,
      4.5,
      1.0,
      4.5,
      1.0,
      1.0,
      1.0,
      1.0,
      5.0,
      1.0,
      4.5,
      1.0,
      1.0,
      4.5,
      1.0,
      4.5,
      1.0,
      4.0,
      1.0,
      1.0,
      1.0,
      4.0,
      5.0,
      1.0
    ]
  },
  "errors_per_bot": {
    "polar_3bettor": 0,
    "v12_cont": 0,
    "squeezer": 0,
    "polar_3bettor_2": 0,
    "squeezer_2": 0,
    "competent_tag": 0,
    "v12_cbet_cont": 0,
    "v12_cbet": 0,
    "v7_m2": 0
  },
  "timing_per_bot": {
    "polar_3bettor": {
      "max": 0.013564763001340907,
      "slow": 0
    },
    "v12_cont": {
      "max": 0.3638941590033937,
      "slow": 0
    },
    "squeezer": {
      "max": 0.0132829469985154,
      "slow": 0
    },
    "polar_3bettor_2": {
      "max": 0.013035052998020547,
      "slow": 0
    },
    "squeezer_2": {
      "max": 0.013365591999900062,
      "slow": 0
    },
    "competent_tag": {
      "max": 0.015659361000871286,
      "slow": 0
    },
    "v12_cbet_cont": {
      "max": 0.08769019299870706,
      "slow": 0
    },
    "v12_cbet": {
      "max": 0.08883196199894883,
      "slow": 0
    },
    "v7_m2": {
      "max": 0.1481819189975795,
      "slow": 0
    }
  },
  "error": null,
  "heroes": [
    {
      "id": "v12_cont",
      "path": "/home/lucas/projects/fullhouse-hackathon-write-up-repo/hero_bots/v12_cont/bot.py"
    },
    {
      "id": "v12_cbet_cont",
      "path": "/home/lucas/projects/fullhouse-hackathon-write-up-repo/hero_bots/v12_cbet_cont/bot.py"
    },
    {
      "id": "v12_cbet",
      "path": "/home/lucas/projects/fullhouse-hackathon-write-up-repo/hero_bots/v12_cbet/bot.py"
    },
    {
      "id": "v7_m2",
      "path": "/home/lucas/projects/fullhouse-hackathon-write-up-repo/hero_bots/v7_m2/bot.py"
    }
  ],
  "baseline": "v12_cont",
  "vs_baseline": {
    "v12_cbet_cont": {
      "stats": {
        "matches": 100,
        "total_delta": -50611,
        "mean_delta": -506.11,
        "stdev": 5873.6241335759005,
        "stderr": 587.3624133575901,
        "ci95": 1151.2303301808765,
        "ci_low": -1657.3403301808767,
        "ci_high": 645.1203301808765,
        "bb_per_100": -0.50611,
        "win_rate": 0.11
      },
      "t_stat": -0.8616656232850858
    },
    "v12_cbet": {
      "stats": {
        "matches": 100,
        "total_delta": -261112,
        "mean_delta": -2611.12,
        "stdev": 10521.79166031291,
        "stderr": 1052.179166031291,
        "ci95": 2062.2711654213304,
        "ci_low": -4673.39116542133,
        "ci_high": -548.8488345786695,
        "bb_per_100": -2.6111199999999997,
        "win_rate": 0.14
      },
      "t_stat": -2.4816305856433836
    },
    "v7_m2": {
      "stats": {
        "matches": 100,
        "total_delta": -75239,
        "mean_delta": -752.39,
        "stdev": 11523.92028194162,
        "stderr": 1152.392028194162,
        "ci95": 2258.6883752605577,
        "ci_low": -3011.0783752605576,
        "ci_high": 1506.2983752605578,
        "bb_per_100": -0.75239,
        "win_rate": 0.18
      },
      "t_stat": -0.6528941380990122
    }
  },
  "per_match_paired": {
    "v12_cbet_cont": [
      0,
      -1100,
      0,
      0,
      -595,
      0,
      0,
      -136,
      0,
      0,
      0,
      13934,
      0,
      0,
      13344,
      960,
      0,
      0,
      0,
      4144,
      470,
      0,
      6528,
      0,
      0,
      0,
      0,
      0,
      0,
      0,
      0,
      0,
      -26261,
      -675,
      0,
      0,
      -1938,
      0,
      0,
      0,
      -2507,
      0,
      0,
      0,
      0,
      0,
      0,
      0,
      0,
      0,
      0,
      -154,
      -2250,
      0,
      0,
      0,
      0,
      -7540,
      700,
      -1800,
      0,
      0,
      0,
      0,
      -40,
      0,
      0,
      -2600,
      0,
      0,
      1905,
      0,
      0,
      0,
      0,
      0,
      700,
      -47148,
      -682,
      0,
      0,
      0,
      0,
      0,
      0,
      0,
      1435,
      1752,
      0,
      0,
      0,
      0,
      0,
      0,
      0,
      0,
      0,
      0,
      0,
      -1057
    ],
    "v12_cbet": [
      0,
      -10182,
      0,
      0,
      13019,
      0,
      0,
      -16470,
      0,
      0,
      0,
      7678,
      -12036,
      0,
      -44983,
      665,
      0,
      0,
      0,
      5000,
      -7777,
      -682,
      14255,
      0,
      0,
      0,
      0,
      0,
      0,
      0,
      0,
      0,
      -26261,
      -521,
      0,
      0,
      466,
      -9902,
      -37077,
      0,
      11906,
      0,
      0,
      1220,
      0,
      0,
      0,
      5966,
      0,
      0,
      -4936,
      -7542,
      -6671,
      0,
      0,
      0,
      0,
      26024,
      -3520,
      -809,
      -23166,
      0,
      -8075,
      0,
      922,
      0,
      0,
      -6206,
      0,
      0,
      -33161,
      -8585,
      0,
      1920,
      0,
      -3022,
      -6774,
      -47148,
      16301,
      0,
      869,
      0,
      0,
      0,
      0,
      -31622,
      -7410,
      -2225,
      0,
      0,
      0,
      0,
      0,
      0,
      0,
      0,
      0,
      0,
      0,
      -560
    ],
    "v7_m2": [
      0,
      -10182,
      0,
      0,
      13019,
      0,
      0,
      -16470,
      60000,
      0,
      0,
      6478,
      -12036,
      0,
      3308,
      -2983,
      0,
      0,
      0,
      5275,
      -11203,
      -1394,
      14208,
      0,
      0,
      0,
      0,
      0,
      0,
      0,
      0,
      0,
      212,
      -471,
      0,
      0,
      92,
      -9902,
      -37077,
      0,
      11906,
      0,
      0,
      1220,
      0,
      0,
      0,
      5966,
      0,
      38130,
      -4936,
      -7867,
      -6671,
      0,
      0,
      0,
      0,
      26024,
      -2920,
      -809,
      -23166,
      0,
      -8075,
      -8566,
      972,
      0,
      0,
      -6601,
      0,
      0,
      -33161,
      -8585,
      0,
      1920,
      0,
      -3414,
      -9674,
      -47148,
      17021,
      0,
      869,
      0,
      0,
      0,
      0,
      0,
      -7410,
      -1488,
      0,
      0,
      0,
      0,
      0,
      0,
      0,
      0,
      0,
      0,
      0,
      350
    ]
  }
}